README.rst
setup.cfg
setup.py
./__init__.py
./review.py
./review.xml
./tryton.cfg
./tests/__init__.py
./tests/test_nereid_review.py
trytond_nereid_review.egg-info/PKG-INFO
trytond_nereid_review.egg-info/SOURCES.txt
trytond_nereid_review.egg-info/dependency_links.txt
trytond_nereid_review.egg-info/entry_points.txt
trytond_nereid_review.egg-info/not-zip-safe
trytond_nereid_review.egg-info/requires.txt
trytond_nereid_review.egg-info/top_level.txt