Metadata-Version: 1.1
Name: trytond-nereid-review
Version: 3.0.1.1
Summary: A pluggable review app
Home-page: http://openlabs.co.in/
Author: Openlabs Technologies and Consulting (P) Ltd.
Author-email: UNKNOWN
License: UNKNOWN
Download-URL: https://github.com/openlabs/nereid-review
Platform: UNKNOWN
Classifier: Development Status :: 4 - Beta
Classifier: Environment :: Plugins
Classifier: Intended Audience :: Developers
Classifier: License :: OSI Approved :: BSD License
Classifier: Natural Language :: English
Classifier: Operating System :: OS Independent
Classifier: Programming Language :: Python
Classifier: Framework :: Tryton
Classifier: Topic :: Office/Business
